salute_speech/__init__.py
salute_speech/exceptions.py
salute_speech/speech_recognition.py
salute_speech/commands/__init__.py
salute_speech/commands/cmd_download_result.py
salute_speech/commands/cmd_get_task_status.py
salute_speech/commands/cmd_recognize_audio.py
salute_speech/commands/cmd_transcribe_audio.py
salute_speech/commands/cmd_upload_audio.py
salute_speech/conf/russian.pem
salute_speech/utils/__init__.py
salute_speech/utils/audio.py
salute_speech/utils/const.py
salute_speech/utils/logging.py
salute_speech/utils/package.py
salute_speech/utils/result_writer.py
salute_speech/utils/russian_certs.py
salute_speech/utils/token.py
salute_speech-1.3.0.dist-info/licenses/LICENSE
salute_speech-1.3.0.dist-info/METADATA
salute_speech-1.3.0.dist-info/WHEEL
salute_speech-1.3.0.dist-info/entry_points.txt
salute_speech-1.3.0.dist-info/top_level.txt
salute_speech-1.3.0.dist-info/RECORD
