Metadata-Version: 2.4
Name: salute_speech
Version: 1.3.0
Summary: Sber Salute Speech API
Author-email: Maxim Moroz <maxim.moroz@gmail.com>
License: MIT License
Project-URL: Homepage, https://github.com/mmua/salute_speech
Project-URL: Repository, https://github.com/mmua/salute_speech.git
Keywords: speech
Classifier: Intended Audience :: Developers
Classifier: Natural Language :: English
Classifier: Programming Language :: Python :: 3.9
Requires-Python: >=3.8
License-File: LICENSE
Requires-Dist: Click>=8.1.7
Requires-Dist: python-dotenv>=1.0.1
Requires-Dist: requests>=2.32.3
Requires-Dist: pydub>=0.25.1
Provides-Extra: test
Requires-Dist: pytest>=7.0.0; extra == "test"
Requires-Dist: pytest-cov>=3.0.0; extra == "test"
Requires-Dist: pytest-mock>=3.7.0; extra == "test"
Requires-Dist: numpy>=1.20.0; extra == "test"
Dynamic: license-file
